sulie/__init__.py
sulie/api.py
sulie/datasets.py
sulie/errors.py
sulie/inference.py
sulie/metrics.py
sulie/tuning.py
sulie/utils.py
sulie-1.0.8.dist-info/METADATA
sulie-1.0.8.dist-info/WHEEL
sulie-1.0.8.dist-info/top_level.txt
sulie-1.0.8.dist-info/RECORD
