Metadata-Version: 2.1
Name: sulie
Version: 1.0.8
Summary: A Python package for interacting with Sulie API
Home-page: https://github.com/wearesulie/sulie
Author: Dominik Safaric
Author-email: hello@sulie.co
Project-URL: Documentation, https://docs.sulie.co
Project-URL: Source, https://github.com/wearesulie/sulie
Project-URL: Tracker, https://github.com/wearesulie/sulie/issues
Classifier: Programming Language :: Python :: 3
Classifier: License :: OSI Approved :: MIT License
Classifier: Operating System :: OS Independent
Requires-Python: >=3.8
Requires-Dist: requests
Requires-Dist: pandas
Requires-Dist: pyarrow
Requires-Dist: tqdm
Requires-Dist: matplotlib
